faro/__init__.py
faro/database.py
faro/table.py
faro-0.0.4.dist-info/LICENSE
faro-0.0.4.dist-info/WHEEL
faro-0.0.4.dist-info/METADATA
faro-0.0.4.dist-info/RECORD
