Metadata-Version: 2.1
Name: faro
Version: 0.0.4
Summary: An SQL-focused data analysis library for Python
Home-page: https://github.com/yanniskatsaros/faro
License: MIT
Keywords: sql,python,data-analysis,data-science,database
Author: Yannis Katsaros
Author-email: yanniskatsaros@hotmail.com
Maintainer: Yannis Katsaros
Maintainer-email: yanniskatsaros@hotmail.com
Requires-Python: >=3.6.1,<4.0.0
Classifier: Development Status :: 2 - Pre-Alpha
Classifier: License :: OSI Approved :: MIT License
Classifier: Operating System :: OS Independent
Classifier: Programming Language :: Python :: 3
Classifier: Programming Language :: Python :: 3.6
Classifier: Programming Language :: Python :: 3.7
Classifier: Programming Language :: Python :: 3.8
Requires-Dist: pandas (>=1.0.3,<2.0.0)
Requires-Dist: pydantic (>=1.5.1,<2.0.0)
Project-URL: Documentation, https://github.com/yanniskatsaros/faro/docs
Project-URL: Repository, https://github.com/yanniskatsaros/faro
